infi_const/__init__.py
infi_const/rabbit_consts.py
infi_const/test_consts.py
infi_const/url_const.py
infi_const/utils_consts.py
infi_conts/__init__.py
infi_conts/url_const.py
infi_conts/utils_consts.py
infi_const-0.0.14.dist-info/METADATA
infi_const-0.0.14.dist-info/WHEEL
infi_const-0.0.14.dist-info/top_level.txt
infi_const-0.0.14.dist-info/RECORD
