Metadata-Version: 2.1
Name: infi-const
Version: 0.0.14
Summary: Const package for infinity team
Author: Infinity Team
License: MIT
